[{"name":"volumedeck_flutter","qualifiedName":"volumedeck_flutter","href":"volumedeck_flutter/volumedeck_flutter-library.html","kind":8,"overriddenDepth":0,"packageRank":0,"desc":""},{"name":"Volumedeck","qualifiedName":"volumedeck_flutter.Volumedeck","href":"volumedeck_flutter/Volumedeck-class.html","kind":3,"overriddenDepth":0,"packageRank":0,"desc":"Volumedeck provides automatic volume adjustment based on GPS speed,\nimproving the media-listening experience for users in vehicles and public transport.","enclosedBy":{"name":"volumedeck_flutter","kind":8,"href":"volumedeck_flutter/volumedeck_flutter-library.html"}},{"name":"Volumedeck","qualifiedName":"volumedeck_flutter.Volumedeck.Volumedeck","href":"volumedeck_flutter/Volumedeck/Volumedeck.html","kind":2,"overriddenDepth":0,"packageRank":0,"desc":"","enclosedBy":{"name":"Volumedeck","kind":3,"href":"volumedeck_flutter/Volumedeck-class.html"}},{"name":"initialize","qualifiedName":"volumedeck_flutter.Volumedeck.initialize","href":"volumedeck_flutter/Volumedeck/initialize.html","kind":9,"overriddenDepth":0,"packageRank":0,"desc":"Initializes Volumedeck with the specified parameters.","enclosedBy":{"name":"Volumedeck","kind":3,"href":"volumedeck_flutter/Volumedeck-class.html"}},{"name":"start","qualifiedName":"volumedeck_flutter.Volumedeck.start","href":"volumedeck_flutter/Volumedeck/start.html","kind":9,"overriddenDepth":0,"packageRank":0,"desc":"","enclosedBy":{"name":"Volumedeck","kind":3,"href":"volumedeck_flutter/Volumedeck-class.html"}},{"name":"stop","qualifiedName":"volumedeck_flutter.Volumedeck.stop","href":"volumedeck_flutter/Volumedeck/stop.html","kind":9,"overriddenDepth":0,"packageRank":0,"desc":"","enclosedBy":{"name":"Volumedeck","kind":3,"href":"volumedeck_flutter/Volumedeck-class.html"}}]
